FMSHProjectGenerator/__init__.py
FMSHProjectGenerator/project_generator.py
FMSHProjectGenerator/assets/project_template.yaml
FMSHProjectGenerator/chips/FM33A04XEH.json
FMSHProjectGenerator/chips/FM33A06XEH.json
FMSHProjectGenerator/chips/FM33FG05XA.json
FMSHProjectGenerator/chips/FM33FG06XA.json
FMSHProjectGenerator/chips/FM33FH02X.json
FMSHProjectGenerator/chips/FM33FH04X.json
FMSHProjectGenerator/chips/FM33FH05X.json
FMSHProjectGenerator/chips/FM33FK52X.json
FMSHProjectGenerator/chips/FM33FK54X.json
FMSHProjectGenerator/chips/FM33FR02X.json
FMSHProjectGenerator/chips/FM33FR04X.json
FMSHProjectGenerator/chips/FM33FR05X.json
FMSHProjectGenerator/chips/FM33FT02XA.json
FMSHProjectGenerator/chips/FM33FT04XA.json
FMSHProjectGenerator/chips/FM33FT05XA.json
FMSHProjectGenerator/chips/FM33HT02XA.json
FMSHProjectGenerator/chips/FM33HT04XA.json
FMSHProjectGenerator/chips/FM33HT05XA.json
FMSHProjectGenerator/chips/FM33LC01X.json
FMSHProjectGenerator/chips/FM33LC02X.json
FMSHProjectGenerator/chips/FM33LC04X.json
FMSHProjectGenerator/chips/FM33LD52X.json
FMSHProjectGenerator/chips/FM33LD54X.json
FMSHProjectGenerator/chips/FM33LE01X.json
FMSHProjectGenerator/chips/FM33LE01XA.json
FMSHProjectGenerator/chips/FM33LE02X.json
FMSHProjectGenerator/chips/FM33LE02XA.json
FMSHProjectGenerator/chips/FM33LF01X.json
FMSHProjectGenerator/chips/FM33LG01X.json
FMSHProjectGenerator/chips/FM33LG02X.json
FMSHProjectGenerator/chips/FM33LG04X.json
FMSHProjectGenerator/chips/FM33LR01X.json
FMSHProjectGenerator/chips/FM33LR02X.json
FMSHProjectGenerator/chips/FM36LV01XA.json
FMSHProjectGenerator/chips/FM36LV02XA.json
FMSHProjectGenerator/chips/FM36LV04XA.json
FMSHProjectGenerator/converters/__init__.py
FMSHProjectGenerator/converters/converter_base.py
FMSHProjectGenerator/converters/iar_converter.py
FMSHProjectGenerator/converters/keil_5_converter.py
FMSHProjectGenerator/generators/__init__.py
FMSHProjectGenerator/generators/generator_base.py
FMSHProjectGenerator/generators/iar_generator.py
fmshprojectgenerator-0.0.25.dist-info/LICENSE.rst
fmshprojectgenerator-0.0.25.dist-info/METADATA
fmshprojectgenerator-0.0.25.dist-info/WHEEL
fmshprojectgenerator-0.0.25.dist-info/entry_points.txt
fmshprojectgenerator-0.0.25.dist-info/top_level.txt
fmshprojectgenerator-0.0.25.dist-info/RECORD
