Metadata-Version: 2.1
Name: FMSHProjectGenerator
Version: 0.0.25
Summary: FMSH(Fudan Microelectronics) general-purpose MCU families IDE project generator.
Author: Zean Huang
Author-email: huangzean@fmsh.com.cn
License: MIT
Classifier: Development Status :: 3 - Alpha
Classifier: Intended Audience :: Developers
Classifier: License :: OSI Approved :: MIT License
Requires-Python: >=3.6
License-File: LICENSE.rst
Requires-Dist: Jinja2>=3.0.2
Requires-Dist: ruamel.yaml>=0.17.9
Requires-Dist: xmltodict>=0.12.0
Requires-Dist: chardet2>=2.0.3
Requires-Dist: click>=8.0.3
